<?xml version='1.0' encoding='UTF-8'?>
<mujoco model="model">
  <compiler angle="radian"/>
  <asset>
    <mesh file="visuals/Body001.obj" name="Body001_vis"/>
    <mesh file="visuals/Button001.obj" name="Button001_vis"/>
    <mesh file="visuals/Button002.obj" name="Button002_vis"/>
    <mesh file="visuals/Button003.obj" name="Button003_vis"/>
    <mesh file="visuals/Container001_Clear.obj" name="Container001_Clear_vis"/>
    <mesh file="visuals/Container002_Clear.obj" name="Container002_Clear_vis"/>
    <mesh file="visuals/Lever001.obj" name="Lever001_vis"/>
    <mesh file="visuals/Lid001.obj" name="Lid001_vis"/>
    <mesh file="visuals/Lid002.obj" name="Lid002_vis"/>
    <mesh file="visuals/Lid003.obj" name="Lid003_vis"/>
    <mesh file="visuals/Lid004.obj" name="Lid004_vis"/>
    <texture file="visuals/T_BC001.png" name="Body001_material" type="2d"/>
    <material name="Body001_material" rgba="1 1 1 1.0" texture="Body001_material" shininess="0.4472135901451111" specular="0.3103448502657381"/>
    <texture file="visuals/T_BC001.png" name="Button001_material" type="2d"/>
    <material name="Button001_material" rgba="1 1 1 1.0" texture="Button001_material" shininess="0.4472135901451111" specular="0.3103448502657381"/>
    <texture file="visuals/T_BC001.png" name="Button002_material" type="2d"/>
    <material name="Button002_material" rgba="1 1 1 1.0" texture="Button002_material" shininess="0.4472135901451111" specular="0.3103448502657381"/>
    <texture file="visuals/T_BC001.png" name="Button003_material" type="2d"/>
    <material name="Button003_material" rgba="1 1 1 1.0" texture="Button003_material" shininess="0.4472135901451111" specular="0.3103448502657381"/>
    <material name="Container001_Clear_material" rgba="0.5 0.5 0.5 0.20000000298023224" shininess="0.4472135901451111" specular="0.3103448502657381"/>
    <texture file="visuals/T_BC001.png" name="Lid003_material" type="2d"/>
    <material name="Lid003_material" rgba="1 1 1 1.0" texture="Lid003_material" shininess="0.4472135901451111" specular="0.3103448502657381"/>
    <material name="Container002_Clear_material" rgba="0.5 0.5 0.5 0.20000000298023224" shininess="0.4472135901451111" specular="0.3103448502657381"/>
    <texture file="visuals/T_BC001.png" name="Lid004_material" type="2d"/>
    <material name="Lid004_material" rgba="1 1 1 1.0" texture="Lid004_material" shininess="0.4472135901451111" specular="0.3103448502657381"/>
    <texture file="visuals/T_BC001.png" name="Lever001_material" type="2d"/>
    <material name="Lever001_material" rgba="1 1 1 1.0" texture="Lever001_material" shininess="0.4472135901451111" specular="0.3103448502657381"/>
    <texture file="visuals/T_BC001.png" name="Lid001_material" type="2d"/>
    <material name="Lid001_material" rgba="1 1 1 1.0" texture="Lid001_material" shininess="0.4472135901451111" specular="0.3103448502657381"/>
    <texture file="visuals/T_BC001.png" name="Lid002_material" type="2d"/>
    <material name="Lid002_material" rgba="1 1 1 1.0" texture="Lid002_material" shininess="0.4472135901451111" specular="0.3103448502657381"/>
  </asset>
  <default>
    <default class="visual">
      <geom conaffinity="0" contype="0" group="1" type="mesh"/>
    </default>
    <default class="collision">
      <geom group="0" rgba="0.5 0 0 0.5"/>
    </default>
    <default class="spawn">
      <geom group="0" rgba="1 1 1 0.5" contype="0" conaffinity="0"/>
      <site group="0" rgba="1 1 1 0.5"/>
    </default>
    <default class="region">
      <geom group="1" conaffinity="0" contype="0" rgba="0 1 0 0"/>
    </default>
  </default>
  <worldbody>
    <body>
      <body name="object">
        <geom class="collision" type="box" pos="0.00730277 -0.13809044 0.09769202" size="0.008365542627871037 9.472201782045886e-05 0.005980726797133684" quat="1.0 0.0 0.0 0.0" name="start_button_1" rgba="0.0 0.5 0 0.5"/>
        <geom class="collision" type="box" pos="0.00730277 -0.13809044 0.04347251" size="0.008365542627871037 9.472201782045886e-05 0.005980726797133684" quat="1.0 0.0 0.0 0.0" name="start_button_2" rgba="0.0 0.5 0 0.5"/>
        <site rgba="0 0 0 0" size="0.009999999776482582 0.009999999776482582" pos="-0.02929676 -0.15692610 -0.08181805" name="receptacle_place_site"/>
        <site type="cylinder" rgba="0.8 0.5 0.25 1" size="0.0026681795716285706 0.08011214435100555" pos="-0.02915555 -0.15706012 -0.03875731" name="coffee_liquid"/>
        <geom mesh="Body001_vis" type="mesh" solimp="0.998 0.998 0.001" solref="0.001 1" density="100" friction="0.95 0.3 0.1" class="visual" material="Body001_material"/>
        <geom class="collision" type="box" pos="-0.07165366 -0.16675430 -0.09807632" size="0.0019627276342362165 0.03125518932938576 0.02139287441968918" quat="1.0 0.0 0.0 0.0"/>
        <geom class="collision" type="box" pos="0.01297871 -0.16675430 -0.09807632" size="0.0019627276342362165 0.03125518932938576 0.02139287441968918" quat="1.0 0.0 0.0 0.0"/>
        <geom class="collision" type="box" pos="-0.02867207 -0.20130060 -0.09807632" size="0.04226496070623398 0.002500868635252118 0.02139287441968918" quat="1.0 0.0 0.0 0.0"/>
        <geom class="collision" type="box" pos="-0.03003570 -0.16755547 -0.11816430" size="0.04090132564306259 0.03143025562167168 0.0013048991095274687" quat="1.0 0.0 0.0 0.0"/>
        <geom class="collision" type="box" pos="-0.02938809 -0.01962217 -0.04223930" size="0.052995678037405014 0.1175687164068222 0.07722990214824677" quat="1.0 0.0 0.0 0.0"/>
        <geom class="collision" type="box" pos="-0.02938809 0.02926141 0.07640921" size="0.052995678037405014 0.0686851441860199 0.03623397275805473" quat="1.0 0.0 0.0 0.0"/>
        <geom class="collision" type="box" pos="-0.07174924 -0.08788503 0.07307968" size="0.0106345284730196 0.04811904951930046 0.03956349566578865" quat="1.0 0.0 0.0 0.0"/>
        <geom class="collision" type="box" pos="0.01359878 -0.08788503 0.07307968" size="0.010470953769981861 0.04811904951930046 0.03956349566578865" quat="1.0 0.0 0.0 0.0"/>
        <geom class="collision" type="box" pos="-0.02898545 -0.13197946 0.07307968" size="0.03391892835497856 0.004024625290185213 0.03956349566578865" quat="1.0 0.0 0.0 0.0"/>
        <geom class="collision" type="box" pos="-0.02910601 -0.15469139 0.07402845" size="0.026945386081933975 0.018662327900528908 0.029040971770882607" quat="1.0 0.0 0.0 0.0"/>
        <geom class="collision" type="box" pos="-0.02928116 0.10798710 -0.11143376" size="0.030186869204044342 0.008108635433018208 0.008645680733025074" quat="1.0 0.0 0.0 0.0"/>
        <geom class="collision" type="cylinder" pos="-0.02910711 0.15158124 -0.10090335" size="0.04720412567257881 0.018325699493288994" quat="1.0 0.0 0.0 0.0"/>
        <geom class="collision" type="cylinder" pos="-0.02905664 -0.15706108 0.04219213" size="0.009545438922941685 0.003457070793956518" quat="1.0 0.0 0.0 0.0"/>
        <body name="Button001">
          <joint axis="0.0 1.0 0.0" pos="0.00738739 -0.13630775 0.09770338" limited="true" name="Button001_joint" range="0.0 0.002" type="slide" damping="1" frictionloss="1" armature=".01" stiffness="0.05"/>
          <geom mesh="Button001_vis" type="mesh" solimp="0.998 0.998 0.001" solref="0.001 1" density="100" friction="0.95 0.3 0.1" class="visual" material="Button001_material"/>
          <geom class="collision" type="box" pos="0.00730277 -0.13700546 0.09769202" size="0.008365542627871037 0.0006880965665914118 0.005980726797133684" quat="1.0 0.0 0.0 0.0"/>
        </body>
        <body name="Button002">
          <joint axis="0.0 1.0 0.0" pos="0.00715084 -0.13630774 0.04343474" limited="true" name="Button002_joint" range="0.0 0.002" type="slide" damping="1" frictionloss="1" armature=".01" stiffness="0.05"/>
          <geom mesh="Button002_vis" type="mesh" solimp="0.998 0.998 0.001" solref="0.001 1" density="100" friction="0.95 0.3 0.1" class="visual" material="Button002_material"/>
          <geom class="collision" type="box" pos="0.00730277 -0.13700546 0.04347251" size="0.008365542627871037 0.0006880965665914118 0.005980726797133684" quat="1.0 0.0 0.0 0.0"/>
        </body>
        <body name="Button003">
          <joint axis="0.0 1.0 0.0" pos="-0.02847257 -0.17429552 0.05660505" limited="true" name="Button003_joint" range="0.0 0.002" type="slide" damping="1" frictionloss="1" armature=".01" stiffness="0.05"/>
          <geom mesh="Button003_vis" type="mesh" solimp="0.998 0.998 0.001" solref="0.001 1" density="100" friction="0.95 0.3 0.1" class="visual" material="Button003_material"/>
          <geom class="collision" type="box" pos="-0.02846008 -0.17477321 0.05677060" size="0.008234042674303055 0.0012075260747224092 0.006142293568700552" quat="1.0 0.0 0.0 0.0"/>
        </body>
        <body name="Container001_Clear">
          <joint axis="0.0 0.0 1.0" pos="-0.03007428 0.15168341 0.01074424" limited="true" name="Container001_Clear_joint" range="0.0 0.08" type="slide" damping="1" frictionloss="1" armature=".01" stiffness="0.05"/>
          <geom mesh="Container001_Clear_vis" type="mesh" solimp="0.998 0.998 0.001" solref="0.001 1" density="100" friction="0.95 0.3 0.1" class="visual" material="Container001_Clear_material"/>
          <geom class="collision" type="cylinder" pos="-0.03034550 0.15158547 -0.07583463" size="0.05222243443131447 0.006352034863084555" quat="1.0 0.0 0.0 0.0"/>
          <geom class="collision" type="box" pos="-0.03073086 0.19498628 0.01940938" size="0.024190563708543777 0.004990540444850922 0.0884857028722763" quat="0.9998824000358582 -0.01533633004873991 -0.0 0.0"/>
          <geom class="collision" type="box" pos="0.01322948 0.15234090 0.01940938" size="0.024190563708543777 0.004990540444850922 0.0884857028722763" quat="0.7070236206054688 -0.01084443461149931 0.010844435542821884 -0.7070236206054688"/>
          <geom class="collision" type="box" pos="-0.02941589 0.10838056 0.01940938" size="0.024190563708543777 0.004990540444850922 0.0884857028722763" quat="7.548901947984632e-08 -1.1578621395003097e-09 0.01533633004873991 -0.9998824000358582"/>
          <geom class="collision" type="box" pos="-0.07337624 0.15102593 0.01940938" size="0.024190563708543777 0.004990540444850922 0.0884857028722763" quat="0.7070236206054688 -0.010844436474144459 -0.010844436474144459 0.7070236206054688"/>
          <geom class="collision" type="box" pos="-0.00058135 0.18343087 0.01940938" size="0.014520161785185337 0.004990539979189634 0.0884857028722763" quat="0.9237709045410156 -0.014168939553201199 0.0058689662255346775 -0.3826383948326111"/>
          <geom class="collision" type="box" pos="0.00132840 0.12184572 0.01940938" size="0.013553086668252945 0.004990539979189634 0.0884857028722763" quat="0.382638543844223 -0.005868968553841114 0.014168938621878624 -0.9237708449363708"/>
          <geom class="collision" type="box" pos="-0.06005243 0.12042298 0.01940938" size="0.0133474450558424 0.004990540910512209 0.0884857028722763" quat="0.38263842463493347 -0.005868967156857252 -0.014168938621878624 0.9237709045410156"/>
          <geom class="collision" type="box" pos="-0.06187089 0.18112538 0.01940938" size="0.015001382678747177 0.004990539979189634 0.0884857028722763" quat="0.9237708449363708 -0.014168930239975452 -0.005868963431566954 0.3826385736465454"/>
          <body name="Lid003">
            <joint axis="0.0 0.0 1.0" pos="-0.02910196 0.15168341 0.10233048" limited="true" name="Lid003_joint" range="0.0 0.05" type="slide" damping="1" frictionloss="1" armature=".01" stiffness="0.05" springref="-10"/>
            <geom mesh="Lid003_vis" type="mesh" solimp="0.998 0.998 0.001" solref="0.001 1" density="100" friction="0.95 0.3 0.1" class="visual" material="Lid003_material"/>
            <geom class="collision" type="cylinder" pos="-0.02904589 0.15186123 0.10275035" size="0.051870137453079224 0.00572917889803648" quat="1.0 0.0 0.0 0.0"/>
          </body>
        </body>
        <body name="Container002_Clear">
          <joint axis="0.0 0.0 1.0" pos="0.05249275 -0.10620883 -0.05565462" limited="true" name="Container002_Clear_joint" range="0.0 0.05" type="slide" damping="1" frictionloss="1" armature=".01" stiffness="0.05"/>
          <geom mesh="Container002_Clear_vis" type="mesh" solimp="0.998 0.998 0.001" solref="0.001 1" density="100" friction="0.95 0.3 0.1" class="visual" material="Container002_Clear_material"/>
          <geom class="collision" type="box" pos="0.05320715 -0.10587975 -0.11444555" size="0.028549982234835625 0.032707907259464264 0.005356448702514172" quat="1.0 0.0 0.0 0.0"/>
          <geom class="collision" type="box" pos="0.02870354 -0.10587975 -0.04986122" size="0.004046385642141104 0.03270791098475456 0.05885925143957138" quat="1.0 0.0 0.0 0.0"/>
          <geom class="collision" type="box" pos="0.07665809 -0.10587975 -0.04986122" size="0.004930246155709028 0.03270791471004486 0.05885925889015198" quat="1.0 0.0 0.0 0.0"/>
          <geom class="collision" type="box" pos="0.05235127 -0.13705213 -0.04986122" size="0.019398266449570656 0.0015355584910139441 0.058859266340732574" quat="1.0 0.0 0.0 0.0"/>
          <geom class="collision" type="box" pos="0.05235127 -0.07532073 -0.04986122" size="0.019398270174860954 0.0015355587238445878 0.05885927751660347" quat="1.0 0.0 0.0 0.0"/>
          <body name="Lid004">
            <joint axis="0.0 0.0 1.0" pos="0.05259326 -0.10618589 0.01971696" limited="true" name="Lid004_joint" range="0.0 0.05" type="slide" damping="1" frictionloss="1" armature=".01" stiffness="0.05"/>
            <geom mesh="Lid004_vis" type="mesh" solimp="0.998 0.998 0.001" solref="0.001 1" density="100" friction="0.95 0.3 0.1" class="visual" material="Lid004_material"/>
            <geom class="collision" type="box" pos="0.05359396 -0.10606719 0.01993344" size="0.028974294662475586 0.03302318975329399 0.021078703925013542" quat="1.0 0.0 0.0 0.0"/>
            <body name="Lever001">
              <joint axis="0.0 -1.0 0.0" pos="0.05243423 -0.13837893 0.02409993" limited="true" name="Lever001_joint" range="0.0 0.6108652381980153" type="hinge" damping="1" frictionloss="1" armature=".01" stiffness="0.01" springref="-0.01"/>
              <geom mesh="Lever001_vis" type="mesh" solimp="0.998 0.998 0.001" solref="0.001 1" density="100" friction="0.95 0.3 0.1" class="visual" material="Lever001_material"/>
              <geom class="collision" type="cylinder" pos="0.05249625 -0.14693167 0.02413832" size="0.007700102403759956 0.007528806105256081" quat="0.7071067094802856 0.7071068286895752 0.0 0.0"/>
              <geom class="collision" type="cylinder" pos="0.04001393 -0.15802739 0.00646839" size="0.008461840450763702 0.038279566913843155" quat="0.908592939376831 0.09292283654212952 0.2880729138851166 0.2878163456916809"/>
            </body>
          </body>
        </body>
        <body name="Lid001">
          <joint axis="0.0 0.0 1.0" pos="-0.02910188 -0.16970975 -0.07552805" limited="true" name="Lid001_joint" range="0.0 0.05" type="slide" damping="1" frictionloss="1" armature=".01" stiffness="0.05" springref="-15"/>
          <geom mesh="Lid001_vis" type="mesh" solimp="0.998 0.998 0.001" solref="0.001 1" density="100" friction="0.95 0.3 0.1" class="visual" material="Lid001_material"/>
          <geom class="collision" type="box" pos="-0.02905987 -0.17144663 -0.07390562" size="0.044556520879268646 0.0323609784245491 0.0022306102328002453" quat="1.0 0.0 0.0 0.0"/>
        </body>
        <body name="Lid002">
          <joint axis="-1.0 0.0 0.0" pos="-0.02910115 -0.04165385 0.10953003" limited="true" name="Lid002_joint" range="0.0 1.5707963267948966" type="hinge" damping="1" frictionloss="1" armature=".01" stiffness="0.05"/>
          <geom mesh="Lid002_vis" type="mesh" solimp="0.998 0.998 0.001" solref="0.001 1" density="100" friction="0.95 0.3 0.1" class="visual" material="Lid002_material"/>
          <geom class="collision" type="box" pos="-0.02911595 -0.08319183 0.10845907" size="0.03118506819009781 0.0429268516600132 0.001685629365965724" quat="1.0 0.0 0.0 0.0"/>
          <geom class="collision" type="box" pos="-0.02914438 -0.12367444 0.11516778" size="0.022576695308089256 0.002444240264594555 0.005167155526578426" quat="1.0 0.0 0.0 0.0"/>
        </body>
        <geom class="region" name="reg_main" type="box" pos="-7.300000000000362e-05 -0.0002889999999999976 -8.74999999999973e-05" size="0.08252895 0.20441936 0.12124719"/>
      </body>
    </body>
  </worldbody>
  <actuator>
    <motor name="Button001_joint_actuator" joint="Button001_joint" gear="0.5"/>
    <motor name="Button002_joint_actuator" joint="Button002_joint" gear="0.5"/>
    <motor name="Button003_joint_actuator" joint="Button003_joint" gear="0.5"/>
    <motor name="Container001_Clear_joint_actuator" joint="Container001_Clear_joint" gear="10"/>
    <motor name="Container002_Clear_joint_actuator" joint="Container002_Clear_joint" gear="10"/>
    <motor name="Lid001_joint_actuator" joint="Lid001_joint" gear="10"/>
    <motor name="Lid002_joint_actuator" joint="Lid002_joint" gear="10"/>
    <motor name="Lid003_joint_actuator" joint="Lid003_joint" gear="10"/>
    <motor name="Lid004_joint_actuator" joint="Lid004_joint" gear="10"/>
    <motor name="Lever001_joint_actuator" joint="Lever001_joint" gear="10"/>
  </actuator>
</mujoco>
