<mujoco model="model">
  <option timestep="0.002" gravity="0.0 0.0 -9.81"/>
  <compiler angle="radian"/>
  <asset>
    <mesh file="visual/Mayonnaise012.obj" name="Mayonnaise012_vis"/>
    <texture file="visual/T_BC001.png" name="Mayonnaise012_material" type="2d"/>
    <material name="Mayonnaise012_material" rgba="1 1 1 1.0" texture="Mayonnaise012_material" shininess="0.4472135901451111" specular="0.3103448502657381"/>
    <mesh file="collision/Mayonnaise012023.obj" name="Mayonnaise012023_mesh"/>
    <mesh file="collision/Mayonnaise012012.obj" name="Mayonnaise012012_mesh"/>
    <mesh file="collision/Mayonnaise012025.obj" name="Mayonnaise012025_mesh"/>
    <mesh file="collision/Mayonnaise012020.obj" name="Mayonnaise012020_mesh"/>
    <mesh file="collision/Mayonnaise012022.obj" name="Mayonnaise012022_mesh"/>
    <mesh file="collision/Mayonnaise012013.obj" name="Mayonnaise012013_mesh"/>
    <mesh file="collision/Mayonnaise012010.obj" name="Mayonnaise012010_mesh"/>
    <mesh file="collision/Mayonnaise012014.obj" name="Mayonnaise012014_mesh"/>
    <mesh file="collision/Mayonnaise012028.obj" name="Mayonnaise012028_mesh"/>
    <mesh file="collision/Mayonnaise012009.obj" name="Mayonnaise012009_mesh"/>
    <mesh file="collision/Mayonnaise012015.obj" name="Mayonnaise012015_mesh"/>
    <mesh file="collision/Mayonnaise012003.obj" name="Mayonnaise012003_mesh"/>
    <mesh file="collision/Mayonnaise012017.obj" name="Mayonnaise012017_mesh"/>
    <mesh file="collision/Mayonnaise012002.obj" name="Mayonnaise012002_mesh"/>
    <mesh file="collision/Mayonnaise012018.obj" name="Mayonnaise012018_mesh"/>
    <mesh file="collision/Mayonnaise012024.obj" name="Mayonnaise012024_mesh"/>
    <mesh file="collision/Mayonnaise012001.obj" name="Mayonnaise012001_mesh"/>
    <mesh file="collision/Mayonnaise012005.obj" name="Mayonnaise012005_mesh"/>
    <mesh file="collision/Mayonnaise012016.obj" name="Mayonnaise012016_mesh"/>
    <mesh file="collision/Mayonnaise012007.obj" name="Mayonnaise012007_mesh"/>
    <mesh file="collision/Mayonnaise012004.obj" name="Mayonnaise012004_mesh"/>
    <mesh file="collision/Mayonnaise012011.obj" name="Mayonnaise012011_mesh"/>
    <mesh file="collision/Mayonnaise012019.obj" name="Mayonnaise012019_mesh"/>
    <mesh file="collision/Mayonnaise012030.obj" name="Mayonnaise012030_mesh"/>
    <mesh file="collision/Mayonnaise012027.obj" name="Mayonnaise012027_mesh"/>
    <mesh file="collision/Mayonnaise012021.obj" name="Mayonnaise012021_mesh"/>
    <mesh file="collision/Mayonnaise012029.obj" name="Mayonnaise012029_mesh"/>
    <mesh file="collision/Mayonnaise012026.obj" name="Mayonnaise012026_mesh"/>
    <mesh file="collision/Mayonnaise012006.obj" name="Mayonnaise012006_mesh"/>
    <mesh file="collision/Mayonnaise012008.obj" name="Mayonnaise012008_mesh"/>
  </asset>
  <default>
    <default class="visual">
      <geom conaffinity="0" contype="0" group="1" type="mesh"/>
    </default>
    <default class="collision">
      <geom group="0" rgba="0.5 0 0 0.5" density="1000.0"/>
    </default>
    <default class="spawn">
      <geom group="0" rgba="1 1 1 0.5" contype="0" conaffinity="0"/>
      <site group="0" rgba="1 1 1 0.5"/>
    </default>
    <default class="region">
      <geom group="1" conaffinity="0" contype="0" rgba="0 1 0 0" mass="0"/>
    </default>
  </default>
  <worldbody>
    <body>
      <body name="object">
        <geom mesh="Mayonnaise012_vis" type="mesh" solimp="0.998 0.998 0.001" solref="0.001 1" friction="0.95 0.3 0.1" class="visual" material="Mayonnaise012_material"/>
        <geom mesh="Mayonnaise012023_mesh" type="mesh" class="collision"/>
        <geom mesh="Mayonnaise012012_mesh" type="mesh" class="collision"/>
        <geom mesh="Mayonnaise012025_mesh" type="mesh" class="collision"/>
        <geom mesh="Mayonnaise012020_mesh" type="mesh" class="collision"/>
        <geom mesh="Mayonnaise012022_mesh" type="mesh" class="collision"/>
        <geom mesh="Mayonnaise012013_mesh" type="mesh" class="collision"/>
        <geom mesh="Mayonnaise012010_mesh" type="mesh" class="collision"/>
        <geom mesh="Mayonnaise012014_mesh" type="mesh" class="collision"/>
        <geom mesh="Mayonnaise012028_mesh" type="mesh" class="collision"/>
        <geom mesh="Mayonnaise012009_mesh" type="mesh" class="collision"/>
        <geom mesh="Mayonnaise012015_mesh" type="mesh" class="collision"/>
        <geom mesh="Mayonnaise012003_mesh" type="mesh" class="collision"/>
        <geom mesh="Mayonnaise012017_mesh" type="mesh" class="collision"/>
        <geom mesh="Mayonnaise012002_mesh" type="mesh" class="collision"/>
        <geom mesh="Mayonnaise012018_mesh" type="mesh" class="collision"/>
        <geom mesh="Mayonnaise012024_mesh" type="mesh" class="collision"/>
        <geom mesh="Mayonnaise012001_mesh" type="mesh" class="collision"/>
        <geom mesh="Mayonnaise012005_mesh" type="mesh" class="collision"/>
        <geom mesh="Mayonnaise012016_mesh" type="mesh" class="collision"/>
        <geom mesh="Mayonnaise012007_mesh" type="mesh" class="collision"/>
        <geom mesh="Mayonnaise012004_mesh" type="mesh" class="collision"/>
        <geom mesh="Mayonnaise012011_mesh" type="mesh" class="collision"/>
        <geom mesh="Mayonnaise012019_mesh" type="mesh" class="collision"/>
        <geom mesh="Mayonnaise012030_mesh" type="mesh" class="collision"/>
        <geom mesh="Mayonnaise012027_mesh" type="mesh" class="collision"/>
        <geom mesh="Mayonnaise012021_mesh" type="mesh" class="collision"/>
        <geom mesh="Mayonnaise012029_mesh" type="mesh" class="collision"/>
        <geom mesh="Mayonnaise012026_mesh" type="mesh" class="collision"/>
        <geom mesh="Mayonnaise012006_mesh" type="mesh" class="collision"/>
        <geom mesh="Mayonnaise012008_mesh" type="mesh" class="collision"/>
        <geom class="region" name="reg_bbox" type="box" pos="-4.0499999999846215e-07 -3.7500000000037503e-07 -0.019914204999999997" size="0.035606015000000005 0.035605045 0.042287985"/>
      </body>
    </body>
  </worldbody>
  <actuator/>
</mujoco>
