<mujoco model="spoon_37">
  <asset>
    <mesh file="visual/model_normalized_0.obj" name="model_normalized_0_vis" scale="0.18 0.18 0.18" refquat="0.4999999999999997 0.4999999999999997 0.4999999999999997 0.4999999999999997"/>
    <mesh file="visual/model_normalized_1.obj" name="model_normalized_1_vis" scale="0.18 0.18 0.18" refquat="0.4999999999999997 0.4999999999999997 0.4999999999999997 0.4999999999999997"/>
    <texture type="2d" name="image0" file="visual/image0.png"/>
    <texture type="2d" name="image3" file="visual/image3.png"/>
    <material name="cuchara" texture="image0" specular="0.5" shininess="0.25"/>
    <material name="mango.001" texture="image3" specular="0.5" shininess="0.25"/>
    <mesh file="collision/collision_mesh_collision_0.obj" name="spoon_collision_mesh_0" scale="0.18 0.18 0.18" refquat="0.4999999999999997 0.4999999999999997 0.4999999999999997 0.4999999999999997"/>
    <mesh file="collision/collision_mesh_collision_1.obj" name="spoon_collision_mesh_1" scale="0.18 0.18 0.18" refquat="0.4999999999999997 0.4999999999999997 0.4999999999999997 0.4999999999999997"/>
  </asset>
  <default>
    <default class="region">
      <geom group="1" conaffinity="0" contype="0" rgba="0 1 0 0"/>
    </default>
    <default class="collision">
      <geom group="0" rgba="0.5 0 0 0.5" density="1000.0"/>
    </default>
  </default>
  <worldbody>
    <body>
      <body name="object">
        <geom solimp="0.998 0.998 0.001" solref="0.001 1" density="100" friction="0.95 0.3 0.1" type="mesh" mesh="model_normalized_0_vis" conaffinity="0" contype="0" group="1" material="mango.001"/>
        <geom solimp="0.998 0.998 0.001" solref="0.001 1" density="100" friction="0.95 0.3 0.1" type="mesh" mesh="model_normalized_1_vis" conaffinity="0" contype="0" group="1" material="cuchara"/>
        <geom class="region" name="reg_bbox" type="box" pos="-8.260925943304187e-09 -5.7882650166539705e-05 -0.00010328245591637578" size="0.018899632573494047 0.09079323118832691 0.006256360599779266"/>
        <geom mesh="spoon_collision_mesh_0" type="mesh" class="collision"/>
        <geom mesh="spoon_collision_mesh_1" type="mesh" class="collision"/>
      </body>
    </body>
  </worldbody>
</mujoco>
